<annotation>
	<folder>images</folder>
	<filename>img79.jpg</filename>
	<path>C:\Users\hp\Desktop\car_detection\images\img79.jpg</path>
	<source>
		<database>Unknown</database>
	</source>
	<size>
		<width>400</width>
		<height>300</height>
		<depth>3</depth>
	</size>
	<segmented>0</segmented>
	<object>
		<name>car</name>
		<pose>Unspecified</pose>
		<truncated>0</truncated>
		<difficult>0</difficult>
		<bndbox>
			<xmin>20</xmin>
			<ymin>70</ymin>
			<xmax>374</xmax>
			<ymax>239</ymax>
		</bndbox>
	</object>
	<object>
		<name>car</name>
		<pose>Unspecified</pose>
		<truncated>0</truncated>
		<difficult>0</difficult>
		<bndbox>
			<xmin>22</xmin>
			<ymin>53</ymin>
			<xmax>135</xmax>
			<ymax>110</ymax>
		</bndbox>
	</object>
	<object>
		<name>car</name>
		<pose>Unspecified</pose>
		<truncated>0</truncated>
		<difficult>0</difficult>
		<bndbox>
			<xmin>124</xmin>
			<ymin>59</ymin>
			<xmax>232</xmax>
			<ymax>111</ymax>
		</bndbox>
	</object>
	<object>
		<name>car</name>
		<pose>Unspecified</pose>
		<truncated>1</truncated>
		<difficult>0</difficult>
		<bndbox>
			<xmin>364</xmin>
			<ymin>77</ymin>
			<xmax>400</xmax>
			<ymax>114</ymax>
		</bndbox>
	</object>
	<object>
		<name>car</name>
		<pose>Unspecified</pose>
		<truncated>0</truncated>
		<difficult>0</difficult>
		<bndbox>
			<xmin>324</xmin>
			<ymin>70</ymin>
			<xmax>365</xmax>
			<ymax>93</ymax>
		</bndbox>
	</object>
</annotation>
