<annotation>
	<folder>images</folder>
	<filename>img42.jpg</filename>
	<path>C:\Users\hp\Desktop\car_detection\images\img42.jpg</path>
	<source>
		<database>Unknown</database>
	</source>
	<size>
		<width>259</width>
		<height>194</height>
		<depth>3</depth>
	</size>
	<segmented>0</segmented>
	<object>
		<name>car</name>
		<pose>Unspecified</pose>
		<truncated>0</truncated>
		<difficult>0</difficult>
		<bndbox>
			<xmin>9</xmin>
			<ymin>83</ymin>
			<xmax>255</xmax>
			<ymax>181</ymax>
		</bndbox>
	</object>
	<object>
		<name>car</name>
		<pose>Unspecified</pose>
		<truncated>0</truncated>
		<difficult>0</difficult>
		<bndbox>
			<xmin>40</xmin>
			<ymin>79</ymin>
			<xmax>105</xmax>
			<ymax>112</ymax>
		</bndbox>
	</object>
	<object>
		<name>car</name>
		<pose>Unspecified</pose>
		<truncated>1</truncated>
		<difficult>0</difficult>
		<bndbox>
			<xmin>1</xmin>
			<ymin>78</ymin>
			<xmax>60</xmax>
			<ymax>118</ymax>
		</bndbox>
	</object>
	<object>
		<name>car</name>
		<pose>Unspecified</pose>
		<truncated>1</truncated>
		<difficult>0</difficult>
		<bndbox>
			<xmin>211</xmin>
			<ymin>84</ymin>
			<xmax>259</xmax>
			<ymax>128</ymax>
		</bndbox>
	</object>
</annotation>
